AUTHORS
COPYING
MANIFEST.in
README.rst
setup.py
django_quickapi.egg-info/PKG-INFO
django_quickapi.egg-info/SOURCES.txt
django_quickapi.egg-info/dependency_links.txt
django_quickapi.egg-info/not-zip-safe
django_quickapi.egg-info/top_level.txt
quickapi/__init__.py
quickapi/apps.py
quickapi/client.py
quickapi/conf.py
quickapi/decorators.py
quickapi/http.py
quickapi/serializers.py
quickapi/tables.py
quickapi/tests.py
quickapi/urls.py
quickapi/views.py
quickapi/locale/en/LC_MESSAGES/django.mo
quickapi/locale/en/LC_MESSAGES/django.po
quickapi/locale/ru/LC_MESSAGES/django.mo
quickapi/locale/ru/LC_MESSAGES/django.po
quickapi/static/bootstrap/3.3.5.quickapi/config.json
quickapi/static/bootstrap/3.3.5.quickapi/css/bootstrap-theme.css
quickapi/static/bootstrap/3.3.5.quickapi/css/bootstrap-theme.min.css
quickapi/static/bootstrap/3.3.5.quickapi/css/bootstrap.css
quickapi/static/bootstrap/3.3.5.quickapi/css/bootstrap.min.css
quickapi/static/bootstrap/3.3.5.quickapi/fonts/glyphicons-halflings-regular.eot
quickapi/static/bootstrap/3.3.5.quickapi/fonts/glyphicons-halflings-regular.svg
quickapi/static/bootstrap/3.3.5.quickapi/fonts/glyphicons-halflings-regular.ttf
quickapi/static/bootstrap/3.3.5.quickapi/fonts/glyphicons-halflings-regular.woff
quickapi/static/bootstrap/3.3.5.quickapi/fonts/glyphicons-halflings-regular.woff2
quickapi/static/bootstrap/3.3.5.quickapi/js/bootstrap.js
quickapi/static/bootstrap/3.3.5.quickapi/js/bootstrap.min.js
quickapi/static/font-awesome/4.4.0/HELP-US-OUT.txt
quickapi/static/font-awesome/4.4.0/css/font-awesome.css
quickapi/static/font-awesome/4.4.0/css/font-awesome.min.css
quickapi/static/font-awesome/4.4.0/fonts/FontAwesome.otf
quickapi/static/font-awesome/4.4.0/fonts/fontawesome-webfont.eot
quickapi/static/font-awesome/4.4.0/fonts/fontawesome-webfont.svg
quickapi/static/font-awesome/4.4.0/fonts/fontawesome-webfont.ttf
quickapi/static/font-awesome/4.4.0/fonts/fontawesome-webfont.woff
quickapi/static/font-awesome/4.4.0/fonts/fontawesome-webfont.woff2
quickapi/static/font-awesome/4.4.0/less/animated.less
quickapi/static/font-awesome/4.4.0/less/bordered-pulled.less
quickapi/static/font-awesome/4.4.0/less/core.less
