Metadata-Version: 1.1
Name: django-quickapi
Version: 3.7.2
Summary: The Django-application for the fast organization API.
Home-page: https://github.com/rosix-ru/django-quickapi/
Author: Grigoriy Kramarenko
Author-email: root@rosix.ru
License: GNU Affero General Public License v3 or later (AGPLv3+)
Platform: any
Classifier: Development Status :: 5 - Production/Stable
Classifier: Environment :: Web Environment
Classifier: Framework :: Django
Classifier: Intended Audience :: Developers
Classifier: License :: OSI Approved :: GNU Affero General Public License v3 or later (AGPLv3+)
Classifier: Natural Language :: Russian
Classifier: Natural Language :: English
Classifier: Operating System :: OS Independent
Classifier: Programming Language :: Python
Classifier: Programming Language :: JavaScript
Classifier: Topic :: Internet :: WWW/HTTP :: Dynamic Content
